[
    {
        "condition": "alternative",
        "terms": [
            {
                "condition": "location_check",
                "offsetY": 1,
                "predicate": {
                    "block": {
                        "tag": "veer:gabil/water_like"
                    }
                }
            },
            {
                "condition": "location_check",
                "offsetY": 1,
                "predicate": {
                    "block": {
                        "state": {
                            "waterlogged": "true"
                        }
                    }
                }
            }
        ]
    }
]